UI4AI/__init__.py
UI4AI/chat_ui.py
UI4AI/conversation_store.py
UI4AI/message_handler.py
UI4AI/session_manager.py
UI4AI/ui_components.py
UI4AI-0.1.2.dist-info/LICENSE
UI4AI-0.1.2.dist-info/METADATA
UI4AI-0.1.2.dist-info/WHEEL
UI4AI-0.1.2.dist-info/top_level.txt
UI4AI-0.1.2.dist-info/RECORD
