Metadata-Version: 2.2
Name: UI4AI
Version: 0.1.2
Summary: A Streamlit UI for LLM chat applications with persistence and chat history
Home-page: https://github.com/DKethan/UI4AI/tree/dev-01
Author: Kethan Dosapati
Keywords: streamlit,chat,ui,llm,chatbot,conversation,ai,openai,UI4AI,UI4AI PYPI,UI4AI package
Classifier: Programming Language :: Python :: 3
Requires-Python: >=3.7
License-File: LICENSE
Requires-Dist: streamlit>=1.20.0
Dynamic: author
Dynamic: classifier
Dynamic: description
Dynamic: description-content-type
Dynamic: home-page
Dynamic: keywords
Dynamic: requires-dist
Dynamic: requires-python
Dynamic: summary
